codeclinic/__init__.py
codeclinic/__main__.py
codeclinic/api.py
codeclinic/ast_scanner.py
codeclinic/cli.py
codeclinic/config.py
codeclinic/graph_analysis.py
codeclinic/graphviz_render.py
codeclinic/json_output.py
codeclinic/stub.py
codeclinic/stub_report.py
codeclinic/types.py
codeclinic-0.1.2.dist-info/METADATA
codeclinic-0.1.2.dist-info/WHEEL
codeclinic-0.1.2.dist-info/entry_points.txt
codeclinic-0.1.2.dist-info/RECORD
