Metadata-Version: 2.4
Name: codeclinic
Version: 0.1.2
Summary: X-ray your Python project: import graph + stub maturity metrics + Graphviz viz + CLI
Project-URL: Homepage, https://github.com/Scienith/code-clinic
Project-URL: Repository, https://github.com/Scienith/code-clinic
Project-URL: Issues, https://github.com/Scienith/code-clinic/issues
Project-URL: Documentation, https://github.com/Scienith/code-clinic#readme
Author-email: CodeClinic Team <codeclinic@example.com>
License: MIT
Keywords: analysis,ast,dependency,graphviz,import,metrics,stub,visualization
Classifier: Development Status :: 4 - Beta
Classifier: Intended Audience :: Developers
Classifier: License :: OSI Approved :: MIT License
Classifier: Programming Language :: Python :: 3
Classifier: Programming Language :: Python :: 3.8
Classifier: Programming Language :: Python :: 3.9
Classifier: Programming Language :: Python :: 3.10
Classifier: Programming Language :: Python :: 3.11
Classifier: Programming Language :: Python :: 3.12
Classifier: Topic :: Software Development :: Libraries :: Python Modules
Classifier: Topic :: Software Development :: Quality Assurance
Requires-Python: >=3.8
Requires-Dist: graphviz>=0.20.1
Requires-Dist: tomli>=2.0.1; python_version < '3.11'
